OnePy/OnePiece.py
OnePy/__init__.py
OnePy/config.py
OnePy/constants.py
OnePy/environment.py
OnePy/event_engine.py
OnePy/builtin_module/__init__.py
OnePy/builtin_module/optimizer.py
OnePy/builtin_module/backtest_forex/__init__.py
OnePy/builtin_module/backtest_forex/calculate_func.py
OnePy/builtin_module/backtest_forex/forex_bar.py
OnePy/builtin_module/backtest_forex/forex_broker.py
OnePy/builtin_module/backtest_forex/forex_log.py
OnePy/builtin_module/backtest_forex/forex_recorder.py
OnePy/builtin_module/backtest_forex/forex_recorder_series.py
OnePy/builtin_module/backtest_stock/__init__.py
OnePy/builtin_module/backtest_stock/stock_bar.py
OnePy/builtin_module/backtest_stock/stock_broker.py
OnePy/builtin_module/backtest_stock/stock_limit_filter_risk_manager.py
OnePy/builtin_module/backtest_stock/stock_log.py
OnePy/builtin_module/backtest_stock/stock_recorder.py
OnePy/builtin_module/backtest_stock/stock_recorder_series.py
OnePy/builtin_module/data_readers/__init__.py
OnePy/builtin_module/data_readers/csvreader.py
OnePy/builtin_module/data_readers/mongodb_reader.py
OnePy/builtin_module/mongodb_saver/__init__.py
OnePy/builtin_module/mongodb_saver/csv_saver.py
OnePy/builtin_module/mongodb_saver/mongodb_config.py
OnePy/builtin_module/mongodb_saver/oanda_saver.py
OnePy/builtin_module/mongodb_saver/tushare_saver.py
OnePy/builtin_module/mongodb_saver/utils.py
OnePy/builtin_module/plotters/__init__.py
OnePy/builtin_module/plotters/by_matplotlib.py
OnePy/builtin_module/plotters/by_plotly.py
OnePy/custom_module/__init__.py
OnePy/custom_module/alpha101_cleaner.py
OnePy/custom_module/analysis.py
OnePy/custom_module/backtest.py
OnePy/custom_module/cleaner_sma.py
OnePy/custom_module/cleaner_talib.py
OnePy/custom_module/forward_analysis.py
OnePy/custom_module/oanda_bar.py
OnePy/custom_module/oanda_broker.py
OnePy/custom_module/oanda_reader.py
OnePy/custom_module/oanda_recorder.py
OnePy/custom_module/trade_log_analysis.py
OnePy/custom_module/api/__init__.py
OnePy_pro-1.1.5.dist-info/LICENSE
OnePy_pro-1.1.5.dist-info/METADATA
OnePy_pro-1.1.5.dist-info/WHEEL
OnePy_pro-1.1.5.dist-info/top_level.txt
OnePy_pro-1.1.5.dist-info/RECORD
